{
  "Ads": [
    {
      "select_main_ads": "ADMOB",
      "select_backup_ads":"APPLOVIN-D",
      "main_ads_banner": "",
      "main_ads_intertitial":"",
      "main_ads_natives":"",
      "main_ads_rewards":"",
      "backup_ads_natives":"",
      "backup_ads_banner":"",
      "backup_ads_intertitial":"",
      "backup_ads_rewards":"",
      "open_ads_admob":"",
      "open_ads_alien":"",
      "switch_open_ads":"1",
      "switch_banner_natives_ads":"",
      "interval_intertitial": 5,
      "initialize_sdk":"",
      "initialize_sdk_backup_ads":"",
      "high_paying_keyword_1": "",
      "high_paying_keyword_2": "",
      "high_paying_keyword_3": "",
      "high_paying_keyword_4": "",
      "high_paying_keyword_5": "",
      "status_app": "0",
      "link_redirect": "https://"
    }
{
  "Categories": [
    {
      "id": 1,
      "name_category": "DJ BREWOG MUSIC",
      "image": "file:///android_asset/image/icon.png"
    }
  ],
  "Data": [
    {
      "id": 1,
      "name_category": "DJ BREWOG MUSIC",
      "title": "DJ SAHUR SAHUR",
      "image": "file:///android_asset/image/icon.png",
      "link_mp3": "mp3/01.mp3",
      "lyrics": "<p style=\"text-align: center;\">DJ BREWOG MUSIC Terlengkap Dan Apli banyak Dicari</p>"
	},
	{
      "id": 2,
      "name_category": "DJ BREWOG MUSIC",
      "title": "DJ POK AME AME",
      "image": "file:///android_asset/image/icon.png",
      "link_mp3": "mp3/02.mp3",
      "lyrics": "<p style=\"text-align: center;\">DJ BREWOG MUSIC Terlengkap Dan Apli banyak Dicari</p>"
	},
	{
      "id": 3,
      "name_category": "DJ BREWOG MUSIC",
      "title": "DJ MARHABAN YA ROMADHAN",
      "image": "file:///android_asset/image/icon.png",
      "link_mp3": "mp3/03.mp3",
      "lyrics": "<p style=\"text-align: center;\">DJ BREWOG MUSIC Terlengkap Dan Apli banyak Dicari</p>"
	},
    {
      "id": 4,
      "name_category": "DJ BREWOG MUSIC",
      "title": "DJ MARS KULI BANGUNAN",
      "image": "file:///android_asset/image/icon.png",
      "link_mp3": "mp3/04.mp3",
      "lyrics": "<p style=\"text-align: center;\">DJ BREWOG MUSIC Terlengkap Dan Apli banyak Dicari</p>"
	},
	{
      "id": 5,
      "name_category": "DJ BREWOG MUSIC",
      "title": "DJ TUKARAN SEMVAK",
      "image": "file:///android_asset/image/icon.png",
      "link_mp3": "mp3/05.mp3",
      "lyrics": "<p style=\"text-align: center;\">DJ BREWOG MUSIC Terlengkap Dan Apli banyak Dicari</p>"
	},
	{
      "id": 6,
      "name_category": "DJ BREWOG MUSIC",
      "title": "DJ BAYAR HUTANG",
      "image": "file:///android_asset/image/icon.png",
      "link_mp3": "mp3/06.mp3",
      "lyrics": "<p style=\"text-align: center;\">DJ BREWOG MUSIC Terlengkap Dan Apli banyak Dicari</p>"
	},
	{
      "id": 7,
      "name_category": "DJ BREWOG MUSIC",
      "title": "DJ LOVE IN THE DARK",
      "image": "file:///android_asset/image/icon.png",
      "link_mp3": "mp3/07.mp3",
      "lyrics": "<p style=\"text-align: center;\">DJ BREWOG MUSIC Terlengkap Dan Apli banyak Dicari</p>"
	},
	{
      "id": 8,
      "name_category": "DJ BREWOG MUSIC",
      "title": "DJ SANAM RE",
      "image": "file:///android_asset/image/icon.png",
      "link_mp3": "mp3/08.mp3",
      "lyrics": "<p style=\"text-align: center;\">DJ BREWOG MUSIC Terlengkap Dan Apli banyak Dicari</p>"
	},
    {
      "id": 9,
      "name_category": "DJ BREWOG MUSIC",
      "title": "DJ SOLAWAT PENYEJUK HATI",
      "image": "file:///android_asset/image/icon.png",
      "link_mp3": "mp3/09.mp3",
      "lyrics": "<p style=\"text-align: center;\">DJ BREWOG MUSIC Terlengkap Dan Apli banyak Dicari</p>"
	},
	{
      "id": 10,
      "name_category": "DJ BREWOG MUSIC",
      "title": "DJ EASY ON ME",
      "image": "file:///android_asset/image/icon.png",
      "link_mp3": "mp3/10.mp3",
      "lyrics": "<p style=\"text-align: center;\">DJ BREWOG MUSIC Terlengkap Dan Apli banyak Dicari</p>"
	},
	{
      "id": 11,
      "name_category": "DJ BREWOG MUSIC",
      "title": "DJ INFONE MASZEE",
      "image": "file:///android_asset/image/icon.png",
      "link_mp3": "mp3/11.mp3",
      "lyrics": "<p style=\"text-align: center;\">DJ BREWOG MUSIC Terlengkap Dan Apli banyak Dicari</p>"
	},
	{
      "id": 12,
      "name_category": "DJ BREWOG MUSIC",
      "title": "DJ PONG PONG X BLA BLA BLA",
      "image": "file:///android_asset/image/icon.png",
      "link_mp3": "mp3/12.mp3",
      "lyrics": "<p style=\"text-align: center;\">DJ BREWOG MUSIC Terlengkap Dan Apli banyak Dicari</p>"
	},
	{
      "id": 13,
      "name_category": "DJ BREWOG MUSIC",
      "title": "DJ OLEJON X OCOPAKELE",
      "image": "file:///android_asset/image/icon.png",
      "link_mp3": "mp3/13.mp3",
      "lyrics": "<p style=\"text-align: center;\">DJ BREWOG MUSIC Terlengkap Dan Apli banyak Dicari</p>"
	},
    {
      "id": 14,
      "name_category": "DJ BREWOG MUSIC",
      "title": "DJ LALI DALANE",
      "image": "file:///android_asset/image/icon.png",
      "link_mp3": "mp3/14.mp3",
      "lyrics": "<p style=\"text-align: center;\">DJ BREWOG MUSIC Terlengkap Dan Apli banyak Dicari</p>"
	},
	{
      "id": 15,
      "name_category": "DJ BREWOG MUSIC",
      "title": "DJ DIDADADU x LELOLAY",
      "image": "file:///android_asset/image/icon.png",
      "link_mp3": "mp3/15.mp3",
      "lyrics": "<p style=\"text-align: center;\">DJ BREWOG MUSIC Terlengkap Dan Apli banyak Dicari</p>"
	},
	{
      "id": 16,
      "name_category": "DJ BREWOG MUSIC",
      "title": "DJ WONDERLAND",
      "image": "file:///android_asset/image/icon.png",
      "link_mp3": "mp3/16.mp3",
      "lyrics": "<p style=\"text-align: center;\">DJ BREWOG MUSIC Terlengkap Dan Apli banyak Dicari</p>"
	},
	{
      "id": 17,
      "name_category": "DJ BREWOG MUSIC",
      "title": "DJ JAVANESE X INFINITY",
      "image": "file:///android_asset/image/icon.png",
      "link_mp3": "mp3/17.mp3",
      "lyrics": "<p style=\"text-align: center;\">DJ BREWOG MUSIC Terlengkap Dan Apli banyak Dicari</p>"
	},
	{
      "id": 18,
      "name_category": "DJ BREWOG MUSIC",
      "title": "DJ INILAH AKU RAJA MEXICO",
      "image": "file:///android_asset/image/icon.png",
      "link_mp3": "mp3/18.mp3",
      "lyrics": "<p style=\"text-align: center;\">DJ BREWOG MUSIC Terlengkap Dan Apli banyak Dicari</p>"
	},
    {
      "id": 19,
      "name_category": "DJ BREWOG MUSIC",
      "title": "DJ INFINITY X UURRAA",
      "image": "file:///android_asset/image/icon.png",
      "link_mp3": "mp3/19.mp3",
      "lyrics": "<p style=\"text-align: center;\">DJ BREWOG MUSIC Terlengkap Dan Apli banyak Dicari</p>"
	},
	{
      "id": 20,
      "name_category": "DJ BREWOG MUSIC",
      "title": "DJ MENIMISYU X UURRAAAA",
      "image": "file:///android_asset/image/icon.png",
      "link_mp3": "mp3/20.mp3",
      "lyrics": "<p style=\"text-align: center;\">DJ BREWOG MUSIC Terlengkap Dan Apli banyak Dicari</p>"
	},
	{
      "id": 21,
      "name_category": "DJ BREWOG MUSIC",
      "title": "DJ MATI MATIAN AKU MENCINTAIMU",
      "image": "file:///android_asset/image/icon.png",
      "link_mp3": "mp3/21.mp3",
      "lyrics": "<p style=\"text-align: center;\">DJ BREWOG MUSIC Terlengkap Dan Apli banyak Dicari</p>"
	},
	{
      "id": 22,
      "name_category": "DJ BREWOG MUSIC",
      "title": "DJ ZAQUE",
      "image": "file:///android_asset/image/icon.png",
      "link_mp3": "mp3/22.mp3",
      "lyrics": "<p style=\"text-align: center;\">DJ BREWOG MUSIC Terlengkap Dan Apli banyak Dicari</p>"
	},
	{
      "id": 23,
      "name_category": "DJ BREWOG MUSIC",
      "title": "DJ DJ GHOST",
      "image": "file:///android_asset/image/icon.png",
      "link_mp3": "mp3/23.mp3",
      "lyrics": "<p style=\"text-align: center;\">DJ BREWOG MUSIC Terlengkap Dan Apli banyak Dicari</p>"
	},
    {
      "id": 24,
      "name_category": "DJ BREWOG MUSIC",
      "title": "DJ RANTAU DAN PANJAUH",
      "image": "file:///android_asset/image/icon.png",
      "link_mp3": "mp3/24.mp3",
      "lyrics": "<p style=\"text-align: center;\">DJ BREWOG MUSIC Terlengkap Dan Apli banyak Dicari</p>"
	},
	{
      "id": 25,
      "name_category": "DJ BREWOG MUSIC",
      "title": "DJ IN THE END",
      "image": "file:///android_asset/image/icon.png",
      "link_mp3": "mp3/25.mp3",
      "lyrics": "<p style=\"text-align: center;\">DJ BREWOG MUSIC Terlengkap Dan Apli banyak Dicari</p>"
	},
	{
      "id": 26,
      "name_category": "DJ BREWOG MUSIC",
      "title": "DJ BABY DONT GO",
      "image": "file:///android_asset/image/icon.png",
      "link_mp3": "mp3/26.mp3",
      "lyrics": "<p style=\"text-align: center;\">DJ BREWOG MUSIC Terlengkap Dan Apli banyak Dicari</p>"
	},
	{
      "id": 27,
      "name_category": "DJ BREWOG MUSIC",
      "title": "DJ PHYTON x COTER GAMAYA",
      "image": "file:///android_asset/image/icon.png",
      "link_mp3": "mp3/27.mp3",
      "lyrics": "<p style=\"text-align: center;\">DJ BREWOG MUSIC Terlengkap Dan Apli banyak Dicari</p>"
	},
	{
      "id": 28,
      "name_category": "DJ BREWOG MUSIC",
      "title": "DJ SLEBOR PARTY",
      "image": "file:///android_asset/image/icon.png",
      "link_mp3": "mp3/28.mp3",
      "lyrics": "<p style=\"text-align: center;\">DJ BREWOG MUSIC Terlengkap Dan Apli banyak Dicari</p>"
	},
    {
      "id": 29,
      "name_category": "DJ BREWOG MUSIC",
      "title": "DJ STYLE STORE LOVE X DARI YANG MUDAe",
      "image": "file:///android_asset/image/icon.png",
      "link_mp3": "mp3/29.mp3",
      "lyrics": "<p style=\"text-align: center;\">DJ BREWOG MUSIC Terlengkap Dan Apli banyak Dicari</p>"
	},
	{
      "id": 30,
      "name_category": "DJ BREWOG MUSIC",
      "title": "DJ JUNGLE DUTCH",
      "image": "file:///android_asset/image/icon.png",
      "link_mp3": "mp3/30.mp3",
      "lyrics": "<p style=\"text-align: center;\">DJ BREWOG MUSIC Terlengkap Dan Apli banyak Dicari</p>"
	},
	{
      "id": 31,
      "name_category": "DJ BREWOG MUSIC",
      "title": "DJ DALAMO DALAMO",
      "image": "file:///android_asset/image/icon.png",
      "link_mp3": "mp3/30.mp3",
      "lyrics": "<p style=\"text-align: center;\">DJ BREWOG MUSIC Terlengkap Dan Apli banyak Dicari</p>"
	},  
	{
      "id": 32,
      "name_category": "DJ BREWOG MUSIC",
      "title": "DJ SUGAR DADDY",
      "image": "file:///android_asset/image/icon.png",
      "link_mp3": "mp3/30.mp3",
      "lyrics": "<p style=\"text-align: center;\">DJ BREWOG MUSIC Terlengkap Dan Apli banyak Dicari</p>"
	},
	{
      "id": 33,
      "name_category": "DJ BREWOG MUSIC",
      "title": "DJ HOREG",
      "image": "file:///android_asset/image/icon.png",
      "link_mp3": "mp3/30.mp3",
      "lyrics": "<p style=\"text-align: center;\">DJ BREWOG MUSIC Terlengkap Dan Apli banyak Dicari</p>"
    },
	{
      "id": 34,
      "name_category": "DJ BREWOG MUSIC",
      "title": "DJ CINTA DALAM LAMUNAN",
      "image": "file:///android_asset/image/icon.png",
      "link_mp3": "mp3/30.mp3",
      "lyrics": "<p style=\"text-align: center;\">DJ BREWOG MUSIC Terlengkap Dan Apli banyak Dicari</p>"
    },
	{
      "id": 35,
      "name_category": "DJ BREWOG MUSIC",
      "title": "DJ LIQUID PLATINUM",
      "image": "file:///android_asset/image/icon.png",
      "link_mp3": "mp3/15.mp3",
      "lyrics": "<p style=\"text-align: center;\">DJ BREWOG MUSIC Terlengkap Dan Apli banyak Dicari</p>"
	},
	{
      "id": 36,
      "name_category": "DJ BREWOG MUSIC",
      "title": "DJ FALLING DEEPER",
      "image": "file:///android_asset/image/icon.png",
      "link_mp3": "mp3/16.mp3",
      "lyrics": "<p style=\"text-align: center;\">DJ BREWOG MUSIC Terlengkap Dan Apli banyak Dicari</p>"
	},
	{
      "id": 37,
      "name_category": "DJ BREWOG MUSIC",
      "title": "DJ GRABY PONTE",
      "image": "file:///android_asset/image/icon.png",
      "link_mp3": "mp3/17.mp3",
      "lyrics": "<p style=\"text-align: center;\">DJ BREWOG MUSIC Terlengkap Dan Apli banyak Dicari</p>"
	},
	{
      "id": 38,
      "name_category": "DJ BREWOG MUSIC",
      "title": "DJ HIDING HALA HALA HIDING",
      "image": "file:///android_asset/image/icon.png",
      "link_mp3": "mp3/18.mp3",
      "lyrics": "<p style=\"text-align: center;\">DJ BREWOG MUSIC Terlengkap Dan Apli banyak Dicari</p>"
	},
    {
      "id": 39,
      "name_category": "DJ BREWOG MUSIC",
      "title": " Brewog feat Aeromax KARA BORUTO",
      "image": "file:///android_asset/image/icon.png",
      "link_mp3": "mp3/19.mp3",
      "lyrics": "<p style=\"text-align: center;\">DJ BREWOG MUSIC Terlengkap Dan Apli banyak Dicari</p>"
	},
	{
      "id": 40,
      "name_category": "DJ BREWOG MUSIC",
      "title": "BASS SUPER PANJANG NJEDUG BIKIN SENAM JANTUNG",
      "image": "file:///android_asset/image/icon.png",
      "link_mp3": "mp3/20.mp3",
      "lyrics": "<p style=\"text-align: center;\">DJ BREWOG MUSIC Terlengkap Dan Apli banyak Dicari</p>"
	},
	{
      "id": 41,
      "name_category": "DJ BREWOG MUSIC",
      "title": "DJ RUNTAH BREWOG",
      "image": "file:///android_asset/image/icon.png",
      "link_mp3": "mp3/21.mp3",
      "lyrics": "<p style=\"text-align: center;\">DJ BREWOG MUSIC Terlengkap Dan Apli banyak Dicari</p>"
	},
	{
      "id": 42,
      "name_category": "DJ BREWOG MUSIC",
      "title": "DJ DARK HOUSE",
      "image": "file:///android_asset/image/icon.png",
      "link_mp3": "mp3/30.mp3",
      "lyrics": "<p style=\"text-align: center;\">DJ BREWOG MUSIC Terlengkap Dan Apli banyak Dicari</p>"
	}
  ]
}